LICENSE
MANIFEST.in
README.md
setup.py
pycausalgps/__init__.py
pycausalgps/erf_helper.py
pycausalgps/exposure_response_function.py
pycausalgps/gps.py
pycausalgps/log.py
pycausalgps/pseudo_population.py
pycausalgps.egg-info/PKG-INFO
pycausalgps.egg-info/SOURCES.txt
pycausalgps.egg-info/dependency_links.txt
pycausalgps.egg-info/top_level.txt
pycausalgps/base/__init__.py
pycausalgps/base/utils.py
pycausalgps/rscripts/__init__.py
pycausalgps/rscripts/rfunctions.py