Metadata-Version: 2.1
Name: pycausalgps
Version: 0.0.3
Summary: Matching on generalized propensity scores with continuous exposures
Home-page: https://github.com/NSAPH-Software/pycausalgps
Author: Naeem Khoshnevis, Xiao Wu, Danielle Braun
Author-email: nkhoshnevis@g.harvard.edu, xw2892@cumc.columbia.edu, dbraun@mail.harvard.edu
Maintainer: Naeem Khoshnevis
Maintainer-email: nkhoshnevis@g.harvard.edu
License: GPL-3
Platform: UNKNOWN
Classifier: Development Status :: 2 - Pre-Alpha
Classifier: Intended Audience :: Science/Research
Classifier: License :: OSI Approved :: GNU General Public License v3 (GPLv3)
Classifier: Natural Language :: English
Classifier: Operating System :: OS Independent
Classifier: Programming Language :: Python :: 3 :: Only
Classifier: Programming Language :: Python :: 3.7
Classifier: Programming Language :: Python :: 3.8
Classifier: Programming Language :: Python :: 3.9
Classifier: Programming Language :: Python :: 3.10
Classifier: Programming Language :: Python :: Implementation :: CPython
Classifier: Programming Language :: Python :: Implementation :: PyPy
Requires-Python: >=3.7
License-File: LICENSE
